dankag/__init__.py
dankag/dankag.py
dankag/models.py
dankag/steps.py
dankag-0.1.1.dist-info/METADATA
dankag-0.1.1.dist-info/WHEEL
dankag-0.1.1.dist-info/top_level.txt
dankag-0.1.1.dist-info/RECORD
